<annotation verified="yes">
	<folder>05-11-2014--UNIDAD DEPORTIVA</folder>
	<filename>2014-11-05T23-24-17Z41151.NVR[UnidadDptva_Central].wmv_frame1900.jpg</filename>
	<path>D:\PDG\dataset_metrocali\labelpls\unidadDeportiva\05-11-2014--UNIDAD DEPORTIVA\2014-11-05T23-24-17Z41151.NVR[UnidadDptva_Central].wmv_frame1900.jpg</path>
	<source>
		<database>Unknown</database>
	</source>
	<size>
		<width>720</width>
		<height>576</height>
		<depth>3</depth>
	</size>
	<segmented>0</segmented>
	<object>
		<name>person</name>
		<pose>Unspecified</pose>
		<truncated>0</truncated>
		<difficult>0</difficult>
		<bndbox>
			<xmin>403</xmin>
			<ymin>261</ymin>
			<xmax>417</xmax>
			<ymax>274</ymax>
		</bndbox>
	</object>
	<object>
		<name>person</name>
		<pose>Unspecified</pose>
		<truncated>0</truncated>
		<difficult>0</difficult>
		<bndbox>
			<xmin>237</xmin>
			<ymin>341</ymin>
			<xmax>261</xmax>
			<ymax>370</ymax>
		</bndbox>
	</object>
	<object>
		<name>person</name>
		<pose>Unspecified</pose>
		<truncated>0</truncated>
		<difficult>0</difficult>
		<bndbox>
			<xmin>235</xmin>
			<ymin>242</ymin>
			<xmax>253</xmax>
			<ymax>260</ymax>
		</bndbox>
	</object>
	<object>
		<name>person</name>
		<pose>Unspecified</pose>
		<truncated>0</truncated>
		<difficult>0</difficult>
		<bndbox>
			<xmin>163</xmin>
			<ymin>297</ymin>
			<xmax>184</xmax>
			<ymax>320</ymax>
		</bndbox>
	</object>
	<object>
		<name>person</name>
		<pose>Unspecified</pose>
		<truncated>0</truncated>
		<difficult>0</difficult>
		<bndbox>
			<xmin>126</xmin>
			<ymin>195</ymin>
			<xmax>141</xmax>
			<ymax>211</ymax>
		</bndbox>
	</object>
	<object>
		<name>person</name>
		<pose>Unspecified</pose>
		<truncated>0</truncated>
		<difficult>0</difficult>
		<bndbox>
			<xmin>310</xmin>
			<ymin>122</ymin>
			<xmax>322</xmax>
			<ymax>134</ymax>
		</bndbox>
	</object>
	<object>
		<name>person</name>
		<pose>Unspecified</pose>
		<truncated>0</truncated>
		<difficult>0</difficult>
		<bndbox>
			<xmin>68</xmin>
			<ymin>269</ymin>
			<xmax>84</xmax>
			<ymax>286</ymax>
		</bndbox>
	</object>
	<object>
		<name>person</name>
		<pose>Unspecified</pose>
		<truncated>0</truncated>
		<difficult>0</difficult>
		<bndbox>
			<xmin>695</xmin>
			<ymin>146</ymin>
			<xmax>706</xmax>
			<ymax>157</ymax>
		</bndbox>
	</object>
	<object>
		<name>person</name>
		<pose>Unspecified</pose>
		<truncated>0</truncated>
		<difficult>0</difficult>
		<bndbox>
			<xmin>355</xmin>
			<ymin>273</ymin>
			<xmax>369</xmax>
			<ymax>289</ymax>
		</bndbox>
	</object>
	<object>
		<name>person</name>
		<pose>Unspecified</pose>
		<truncated>0</truncated>
		<difficult>0</difficult>
		<bndbox>
			<xmin>116</xmin>
			<ymin>137</ymin>
			<xmax>129</xmax>
			<ymax>150</ymax>
		</bndbox>
	</object>
	<object>
		<name>person</name>
		<pose>Unspecified</pose>
		<truncated>0</truncated>
		<difficult>0</difficult>
		<bndbox>
			<xmin>19</xmin>
			<ymin>189</ymin>
			<xmax>33</xmax>
			<ymax>203</ymax>
		</bndbox>
	</object>
	<object>
		<name>person</name>
		<pose>Unspecified</pose>
		<truncated>0</truncated>
		<difficult>0</difficult>
		<bndbox>
			<xmin>159</xmin>
			<ymin>122</ymin>
			<xmax>174</xmax>
			<ymax>135</ymax>
		</bndbox>
	</object>
	<object>
		<name>person</name>
		<pose>Unspecified</pose>
		<truncated>0</truncated>
		<difficult>0</difficult>
		<bndbox>
			<xmin>30</xmin>
			<ymin>273</ymin>
			<xmax>43</xmax>
			<ymax>288</ymax>
		</bndbox>
	</object>
	<object>
		<name>person</name>
		<pose>Unspecified</pose>
		<truncated>0</truncated>
		<difficult>0</difficult>
		<bndbox>
			<xmin>668</xmin>
			<ymin>110</ymin>
			<xmax>680</xmax>
			<ymax>122</ymax>
		</bndbox>
	</object>
	<object>
		<name>person</name>
		<pose>Unspecified</pose>
		<truncated>0</truncated>
		<difficult>0</difficult>
		<bndbox>
			<xmin>264</xmin>
			<ymin>91</ymin>
			<xmax>271</xmax>
			<ymax>98</ymax>
		</bndbox>
	</object>
	<object>
		<name>person</name>
		<pose>Unspecified</pose>
		<truncated>0</truncated>
		<difficult>0</difficult>
		<bndbox>
			<xmin>134</xmin>
			<ymin>134</ymin>
			<xmax>145</xmax>
			<ymax>146</ymax>
		</bndbox>
	</object>
	<object>
		<name>person</name>
		<pose>Unspecified</pose>
		<truncated>0</truncated>
		<difficult>0</difficult>
		<bndbox>
			<xmin>604</xmin>
			<ymin>109</ymin>
			<xmax>613</xmax>
			<ymax>120</ymax>
		</bndbox>
	</object>
</annotation>
